CHANGES.txt
README.txt
buildout.cfg
setup.py
bootstrap/bootstrap.py
z3c/__init__.py
z3c.recipe.template.egg-info/PKG-INFO
z3c.recipe.template.egg-info/SOURCES.txt
z3c.recipe.template.egg-info/dependency_links.txt
z3c.recipe.template.egg-info/entry_points.txt
z3c.recipe.template.egg-info/namespace_packages.txt
z3c.recipe.template.egg-info/not-zip-safe
z3c.recipe.template.egg-info/requires.txt
z3c.recipe.template.egg-info/top_level.txt
z3c/recipe/__init__.py
z3c/recipe/template/README.txt
z3c/recipe/template/__init__.py
z3c/recipe/template/tests.py