Metadata-Version: 1.0
Name: z3c.recipe.template
Version: 0.1
Summary: Buildout recipe to generate a text file from a template
Home-page: http://pypi.python.org/pypi/z3c.recipe.template
Author: Uli Fouquet based on work of Wichert Akkerman
Author-email: grok-dev@zope.org
License: ZPL 2.1
Keywords: template buildout zope
Platform: UNKNOWN
Classifier: Development Status :: 3 - Alpha
Classifier: Framework :: Buildout
Classifier: Programming Language :: Python
Classifier: Topic :: Software Development :: Libraries :: Python Modules
Classifier: License :: OSI Approved :: Zope Public License
